release_info/__init__.py
release_info/__main__.py
release_info/release_info.py
release_info-0.3.6.dist-info/LICENSE
release_info-0.3.6.dist-info/METADATA
release_info-0.3.6.dist-info/WHEEL
release_info-0.3.6.dist-info/entry_points.txt
release_info-0.3.6.dist-info/namespace_packages.txt
release_info-0.3.6.dist-info/top_level.txt
release_info-0.3.6.dist-info/RECORD
