Metadata-Version: 2.1
Name: release-info
Version: 0.3.6
Summary: automatically updated python release information
Home-page: https://sourceforge.net/p/release-info/code/ci/default/tree
Author: Anthon van der Neut
Author-email: a.van.der.neut@ruamel.eu
License: Copyright Ruamel bvba 2007-2020
Keywords: pypi statistics
Platform: UNKNOWN
Classifier: Development Status :: 4 - Beta
Classifier: Intended Audience :: Developers
Classifier: License :: Other/Proprietary License
Classifier: Operating System :: OS Independent
Classifier: Programming Language :: Python
Requires-Python: >=3
License-File: LICENSE
